[
    {
        "Currency": "wKbsY",
        "Currency_Text": "Currency_Text1"
    },
    {
        "Currency": "EKSEN",
        "Currency_Text": "Currency_Text2"
    },
    {
        "Currency": "IMQrj",
        "Currency_Text": "Currency_Text3"
    },
    {
        "Currency": "zUuIL",
        "Currency_Text": "Currency_Text4"
    },
    {
        "Currency": "haOIO",
        "Currency_Text": "Currency_Text5"
    },
    {
        "Currency": "Qnrao",
        "Currency_Text": "Currency_Text6"
    },
    {
        "Currency": "txmxx",
        "Currency_Text": "Currency_Text7"
    },
    {
        "Currency": "PgtNO",
        "Currency_Text": "Currency_Text8"
    },
    {
        "Currency": "XFaeR",
        "Currency_Text": "Currency_Text9"
    },
    {
        "Currency": "XLcPB",
        "Currency_Text": "Currency_Text10"
    },
    {
        "Currency": "uUrxn",
        "Currency_Text": "Currency_Text11"
    },
    {
        "Currency": "PgTYq",
        "Currency_Text": "Currency_Text12"
    },
    {
        "Currency": "hcBEU",
        "Currency_Text": "Currency_Text13"
    },
    {
        "Currency": "Gngxn",
        "Currency_Text": "Currency_Text14"
    },
    {
        "Currency": "GHAOO",
        "Currency_Text": "Currency_Text15"
    },
    {
        "Currency": "MsLYn",
        "Currency_Text": "Currency_Text16"
    },
    {
        "Currency": "TXhlr",
        "Currency_Text": "Currency_Text17"
    },
    {
        "Currency": "AsPIz",
        "Currency_Text": "Currency_Text18"
    },
    {
        "Currency": "WdkMl",
        "Currency_Text": "Currency_Text19"
    },
    {
        "Currency": "ndrCp",
        "Currency_Text": "Currency_Text20"
    }
]